dataservice/__init__.py
dataservice/_utils.py
dataservice/cache.py
dataservice/cli.py
dataservice/clients.py
dataservice/config.py
dataservice/data.py
dataservice/devices.py
dataservice/exceptions.py
dataservice/files.py
dataservice/logs.py
dataservice/models.py
dataservice/service.py
dataservice/templates/template.py.j2
dataservice/worker.py
python_dataservice-0.14.0.dist-info/LICENSE
python_dataservice-0.14.0.dist-info/METADATA
python_dataservice-0.14.0.dist-info/WHEEL
python_dataservice-0.14.0.dist-info/entry_points.txt
python_dataservice-0.14.0.dist-info/RECORD
