Metadata-Version: 2.1
Name: python-dataservice
Version: 0.14.0
Summary: Lightweight async data gathering for Python
License: MIT
Keywords: async,data gathering,scraping,web scraping,web crawling,crawling,data extraction,data scraping,API,data
Author: NomadMonad
Author-email: romagnoli.luca@gmail.com
Requires-Python: >=3.11,<4.0
Classifier: License :: OSI Approved :: MIT License
Classifier: Programming Language :: Python :: 3
Classifier: Programming Language :: Python :: 3.11
Classifier: Programming Language :: Python :: 3.12
Classifier: Programming Language :: Python :: 3.13
Provides-Extra: playwright
Requires-Dist: aiolimiter (>=1.1.0,<2.0.0)
Requires-Dist: bs4 (>=0.0.2,<0.0.3)
Requires-Dist: html5lib (>=1.1,<2.0)
Requires-Dist: httpx (>=0.27.0,<0.28.0)
Requires-Dist: jinja2 (>=3.1.4,<4.0.0)
Requires-Dist: playwright (>=1.48.0,<2.0.0) ; extra == "playwright"
Requires-Dist: pydantic (>=2.8.2,<3.0.0)
Requires-Dist: tenacity (>=9.0.0,<10.0.0)
Project-URL: Documentation, https://readthedocs.org/projects/dataservice/
